data_operations/__init__.py
data_operations/data_operations.py
data_operations-0.0.2.dist-info/LICENSE
data_operations-0.0.2.dist-info/METADATA
data_operations-0.0.2.dist-info/WHEEL
data_operations-0.0.2.dist-info/top_level.txt
data_operations-0.0.2.dist-info/RECORD
