Metadata-Version: 2.1
Name: data-operations
Version: 0.0.2
Summary: Pacote para manipular um banco de dados.
Author: Caio da Silva Rocha
Author-email: brothercaio20123@gmail.com
Classifier: Programming Language :: Python :: 3
Classifier: License :: OSI Approved :: MIT License
Classifier: Operating System :: OS Independent
Requires-Python: >=3.8
License-File: LICENSE
